Workbook

Sheet Raw Data 
A1: SOUTHWEST AIRLINES CO. (NYSE: LUV)
A2: Raw Data - FY2025 10-K
A3: Source: SEC EDGAR, luv-20251231.htm
A5: INCOME STATEMENT
B6: 2025 Amount ($M) | C6: 2024 Amount ($M) | D6: 2023 Amount ($M) | E6: Source | F6: Notes
A7: Total operating revenues | B7: 28063 | C7: 27483 | D7: 26091 | E7: 10-K p.85 | F7: From Consolidated Statement of Income
A8: Operating income (loss) | B8: 428 | C8: 321 | D8: 224 | E8: 10-K p.85 | F8: From Consolidated Statement of Income
A9: Interest expense | B9: 167 | C9: 249 | D9: 259 | E9: 10-K p.85 | F9: From Consolidated Statement of Income
A11: CASHFLOW STATEMENT
B12: 2025 Amount ($M) | C12: 2024 Amount ($M) | D12: 2023 Amount ($M) | E12: Source | F12: Notes
A13: Depreciation and amortization | B13: 1560 | C13: 1657 | D13: 1522 | E13: 10-K p.88 | F13: From Consolidated Statement of Cash Flows
A14: Capital expenditure | B14: -2673 | C14: -2054 | D14: -3520 | E14: 10-K p.88 | F14: From Consolidated Statement of Cash Flows
A15: Net cash from operating activities | B15: 1842 | C15: 462 | D15: 3164 | E15: 10-K p.88 | F15: From Consolidated Statement of Cash Flows
A17: BALANCE SHEET
B18: 2025 Amount ($M) | C18: 2024 Amount ($M) | D18: 2023 Amount ($M) | E18: Source | F18: Notes
A19: Total current assets | B19: 5645 | C19: 11274 | D19: 13955 | E19: 10-K p.84 | F19: From Consolidated Balance Sheet
A20: Total current liabilities | B20: 10921 | C20: 12276 | D20: 12256 | E20: 10-K p.84 | F20: From Consolidated Balance Sheet
A21: Long-term debt | B21: 4577 | C21: 5069 | D21: 7978 | E21: 10-K p.84 | F21: From Consolidated Balance Sheet
A22: Air Traffic Liability | B22: 5945 | C22: 6294 | D22: 6551 | E22: 10-K p.84 | F22: From Consolidated Balance Sheet
A23: Total assets | B23: 29061 | C23: 33750 | D23: 36487 | E23: 10-K p.84 | F23: From Consolidated Balance Sheet
A24: Accounts payables | B24: 1991 | C24: 1818 | D24: 1862 | E24: 10-K p.84 | F24: From Consolidated Balance Sheet

Sheet Ratio Analysis
A1: SOUTHWEST AIRLINES - RATIO ANALYSIS
A2: Source: Raw Data Tab, FY2025 10-K + Q1 2026 10-Q
A4: Ratio | B4: 2025 | C4: 2024 | D4: 2023 | E4: Benchmark | F4: Flag | G4: Interpretation
A5: EBITDA | B5: ='Raw Data '!B8+'Raw Data '!B13 -> 1988 | C5: ='Raw Data '!C8+'Raw Data '!C13 -> 1978 | D5: ='Raw Data '!D8+'Raw Data '!D13 -> 1746 | E5: - | F5: - | G5: Operating cash earnings before interest, taxes, D&A
A6: EBITDA/ Interest | B6: =B5/'Raw Data '!B9 -> 11.904192 | C6: =C5/'Raw Data '!C9 -> 7.9437751 | D6: =D5/'Raw Data '!D9 -> 6.7413127 | E6: > 2.0x | F6: =IF(B6>3,"Good",IF(B6>=2,"Neutral","Bad")) -> Good | G6: Years of EBITDA needed to repay all debt
A7: Debt/ EBITDA | B7: ='Raw Data '!B21/'Ratio Analysis'!B5 -> 2.3023139 | C7: ='Raw Data '!C21/'Ratio Analysis'!C5 -> 2.5626896 | D7: ='Raw Data '!D21/'Ratio Analysis'!D5 -> 4.5693013 | E7: 3.0x - 5.0x (airline avg) | F7: =IF(B7<3,"Good",IF(B7<5,"Neutral","Bad")) -> Good | G7: Ability to cover interest payments from operating earnings
A8: Current Ratio | B8: ='Raw Data '!B19/'Raw Data '!B20 -> 0.51689406 | C8: ='Raw Data '!C19/'Raw Data '!C20 -> 0.91837732 | D8: ='Raw Data '!D19/'Raw Data '!D20 -> 1.138626 | E8: > 1.0x | F8: =IF(B8>3,"Good",IF(B8<=5,"Neutral","Bad")) -> Neutral | G8: Note: airlines carry Air Traffic Liability — may understate true liquidity
A9: Adjusted Current Ratio | B9: ='Raw Data '!B19/('Raw Data '!B20-'Raw Data '!B22) -> 1.1344453 | C9: ='Raw Data '!C19/('Raw Data '!C20-'Raw Data '!C22) -> 1.884654 | D9: ='Raw Data '!D19/('Raw Data '!D20-'Raw Data '!D22) -> 2.4460999 | E9: > 1.0x | F9: =IF(B9>1,"Good",IF(B9<=1,"Neutral","Bad")) -> Good
A10: Days Payable Outstanding | B10: =('Raw Data '!B24/'Raw Data '!B7)*365 -> 25.895841 | C10: =('Raw Data '!C24/'Raw Data '!C7)*365 -> 24.144744 | D10: =('Raw Data '!D24/'Raw Data '!D7)*365 -> 26.048446 | E10: < 45 days | F10: =IF(B10<45,"Good",IF(B10>45,"Neutral","Bad")) -> Good | G10: How long the company takes to pay its own bills
A11: Debt/ Total Assets | B11: ='Raw Data '!B21/'Raw Data '!B23 -> 0.1574963 | C11: ='Raw Data '!C21/'Raw Data '!C23 -> 0.15019259 | D11: ='Raw Data '!D21/'Raw Data '!D23 -> 0.21865322 | E11: < 60% | F11: =IF(B11<0.6,"Good",IF(B11>=0.6,"Neutral","Bad")) -> Good | G11: Share of assets financed by debt

Sheet Scenario Analysis 
A1: SOUTHWEST AIRLINES - SCENARIO ANALYSIS
A2: Base, adverse, and severely adverse stress testing
A4: Metric | B4: Revenue Growth | C4: EBITDA Margin
A5: Base | B5: 0.02 | C5: 0.0709
A6: Adverse | B6: -0.15 | C6: 0.0309
A7: Severely Adverse | B7: -0.3 | C7: -0.0091
A9: BASE CASE - PROJECTED FINANCIALS AND RATIOS
B10: 2025 | C10: 2026 | D10: 2027 | E10: 2028 | I10: 2030
A11: Revenue | B11: ='Raw Data '!B7 -> 28063 | C11: =B11*(1+$B$5) -> 28624.26 | D11: =C11*(1+$B$5) -> 29196.745 | E11: =D11*(1+$B$5) -> 29780.68
A12: EBITDA | B12: ='Ratio Analysis'!B5 -> 1988 | C12: =C11*$C$5 -> 2029.46 | D12: =D11*$C$5 -> 2070.0492 | E12: =E11*$C$5 -> 2111.4502
A13: Debt / EBITDA | B13: ='Raw Data '!$B$21/'Scenario Analysis '!B12 -> 2.3023139 | C13: ='Raw Data '!$B$21/'Scenario Analysis '!C12 -> 2.2552797 | D13: ='Raw Data '!$B$21/'Scenario Analysis '!D12 -> 2.2110585 | E13: ='Raw Data '!$B$21/'Scenario Analysis '!E12 -> 2.1677044
A14: EBITDA / Interest | B14: =B12/'Raw Data '!$B$9 -> 11.904192 | C14: =C12/'Raw Data '!$B$9 -> 12.152455 | D14: =D12/'Raw Data '!$B$9 -> 12.395504 | E14: =E12/'Raw Data '!$B$9 -> 12.643414
A15: DPO | B15: =('Raw Data '!$B$24/'Scenario Analysis '!B11)*365 -> 25.895841 | C15: =('Raw Data '!$B$24/'Scenario Analysis '!C11)*365 -> 25.38808 | D15: =('Raw Data '!$B$24/'Scenario Analysis '!D11)*365 -> 24.890274 | E15: =('Raw Data '!$B$24/'Scenario Analysis '!E11)*365 -> 24.40223
A17: ADVERSE CASE - PROJECTED FINANCIALS AND RATIOS
B18: 2025 | C18: 2026 | D18: 2027 | E18: 2028
A19: Revenue | B19: ='Raw Data '!B7 -> 28063 | C19: =B19*(1+$B$6) -> 23853.55 | D19: =C19*(1+$B$6) -> 20275.517 | E19: =D19*(1+$B$6) -> 17234.19
A20: EBITDA | B20: ='Ratio Analysis'!B5 -> 1988 | C20: =C19*$C$6 -> 737.0747 | D20: =D19*$C$6 -> 626.51349 | E20: =E19*$C$6 -> 532.53647
A21: Debt / EBITDA | B21: ='Raw Data '!$B$21/'Scenario Analysis '!B20 -> 2.3023139 | C21: ='Raw Data '!$B$21/'Scenario Analysis '!C20 -> 6.2096827 | D21: ='Raw Data '!$B$21/'Scenario Analysis '!D20 -> 7.3055091 | E21: ='Raw Data '!$B$21/'Scenario Analysis '!E20 -> 8.5947166
A22: EBITDA / Interest | B22: =B20/'Raw Data '!$B$9 -> 11.904192 | C22: =C20/'Raw Data '!$B$9 -> 4.4136209 | D22: =D20/'Raw Data '!$B$9 -> 3.7515778 | E22: =E20/'Raw Data '!$B$9 -> 3.1888411
A23: DPO | B23: =('Raw Data '!$B$24/'Scenario Analysis '!B19)*365 -> 25.895841 | C23: =('Raw Data '!$B$24/'Scenario Analysis '!C19)*365 -> 30.465696 | D23: =('Raw Data '!$B$24/'Scenario Analysis '!D19)*365 -> 35.841995 | E23: =('Raw Data '!$B$24/'Scenario Analysis '!E19)*365 -> 42.167053
A25: SEVERELY ADVERSE CASE - PROJECTED FINANCIALS AND RATIOS
B26: 2025 | C26: 2026 | D26: 2027 | E26: 2028
A27: Revenue | B27: ='Raw Data '!B7 -> 28063 | C27: =B27*(1+$B$7) -> 19644.1 | D27: =C27*(1+$B$7) -> 13750.87 | E27: =D27*(1+$B$7) -> 9625.609
A28: EBITDA | B28: ='Ratio Analysis'!B5 -> 1988 | C28: =C27*$C$7 -> -178.76131 | D28: =D27*$C$7 -> -125.13292 | E28: =E27*$C$7 -> -87.593042
A29: Debt / EBITDA | B29: ='Raw Data '!$B$21/'Scenario Analysis '!B20 -> 2.3023139 | C29: =IF(C28<0,"N/M",'Raw Data '!$B$21/'Scenario Analysis '!C28) -> N/M | D29: =IF(D28<0,"N/M",'Raw Data '!$B$21/'Scenario Analysis '!D28) -> N/M | E29: =IF(E28<0,"N/M",'Raw Data '!$B$21/'Scenario Analysis '!E28) -> N/M
A30: EBITDA / Interest | B30: =B28/'Raw Data '!$B$9 -> 11.904192 | C30: =IF(C28<0,"N/M",C28/'Raw Data '!$B$9) -> N/M | D30: =IF(D28<0,"N/M",D28/'Raw Data '!$B$9) -> N/M | E30: =IF(E28<0,"N/M",E28/'Raw Data '!$B$9) -> N/M
A31: DPO | B31: =('Raw Data '!$B$24/'Scenario Analysis '!B27)*365 -> 25.895841 | C31: =('Raw Data '!$B$24/'Scenario Analysis '!C27)*365 -> 36.994059 | D31: =('Raw Data '!$B$24/'Scenario Analysis '!D27)*365 -> 52.848656 | E31: =('Raw Data '!$B$24/'Scenario Analysis '!E27)*365 -> 75.49808
